[{"claim": "New Zealand Labour Party is talking about a forced coronavirus vaccination", "id": 29, "source": "AFP Fact Check New Zealand", "root_tweet": {"id": 1267229347804352512, "text": "", "stance": "Discussing", "leaning": "Supporting", "children": []}},
{"claim": "New Zealand Labour Party is talking about a forced coronavirus vaccination", "id": 29, "source": "AFP Fact Check New Zealand", "root_tweet": {"id": 1292593514182782978, "text": "", "stance": "Irrelevant", "leaning": "", "children": []}},
{"claim": "New Zealand Labour Party is talking about a forced coronavirus vaccination", "id": 29, "source": "AFP Fact Check New Zealand", "root_tweet": {"id": 1303879148360744960, "text": "", "stance": "Discussing", "leaning": "Supporting", "children": []}},
{"claim": "New Zealand Labour Party is talking about a forced coronavirus vaccination", "id": 29, "source": "AFP Fact Check New Zealand", "root_tweet": {"id": 1298106108343705600, "text": "", "stance": "Discussing", "leaning": "Refuting", "children": []}},
{"claim": "New Zealand Labour Party is talking about a forced coronavirus vaccination", "id": 29, "source": "AFP Fact Check New Zealand", "root_tweet": {"id": 1297145468380762112, "text": "", "stance": "Supporting", "leaning": "", "children": []}},
{"claim": "New Zealand Labour Party is talking about a forced coronavirus vaccination", "id": 29, "source": "AFP Fact Check New Zealand", "root_tweet": {"id": 1296155566679691265, "text": "", "stance": "Irrelevant", "leaning": "", "children": []}},
{"claim": "New Zealand Labour Party is talking about a forced coronavirus vaccination", "id": 29, "source": "AFP Fact Check New Zealand", "root_tweet": {"id": 1323966471224107008, "text": "", "stance": "Discussing", "leaning": "", "children": []}},
{"claim": "New Zealand Labour Party is talking about a forced coronavirus vaccination", "id": 29, "source": "AFP Fact Check New Zealand", "root_tweet": {"id": 1300547671627837441, "text": "", "stance": "Discussing", "leaning": "Supporting", "children": []}},
{"claim": "New Zealand Labour Party is talking about a forced coronavirus vaccination", "id": 29, "source": "AFP Fact Check New Zealand", "root_tweet": {"id": 1338293962076004352, "text": "", "stance": "Supporting", "leaning": "", "children": []}},
{"claim": "New Zealand Labour Party is talking about a forced coronavirus vaccination", "id": 29, "source": "AFP Fact Check New Zealand", "root_tweet": {"id": 1298763035167711232, "text": "", "stance": "Discussing", "leaning": "", "children": []}},
{"claim": "New Zealand Labour Party is talking about a forced coronavirus vaccination", "id": 29, "source": "AFP Fact Check New Zealand", "root_tweet": {"id": 1295881574802579457, "text": "", "stance": "Discussing", "leaning": "Supporting", "children": []}},
{"claim": "New Zealand Labour Party is talking about a forced coronavirus vaccination", "id": 29, "source": "AFP Fact Check New Zealand", "root_tweet": {"id": 1297107080915177472, "text": "", "stance": "Irrelevant", "leaning": "", "children": []}},
{"claim": "New Zealand Labour Party is talking about a forced coronavirus vaccination", "id": 29, "source": "AFP Fact Check New Zealand", "root_tweet": {"id": 1298473649209348096, "text": "", "stance": "Irrelevant", "leaning": "", "children": []}},
{"claim": "New Zealand Labour Party is talking about a forced coronavirus vaccination", "id": 29, "source": "AFP Fact Check New Zealand", "root_tweet": {"id": 1300547447874359296, "text": "", "stance": "Irrelevant", "leaning": "", "children": []}},
{"claim": "New Zealand Labour Party is talking about a forced coronavirus vaccination", "id": 29, "source": "AFP Fact Check New Zealand", "root_tweet": {"id": 1298989691245481984, "text": "", "stance": "Irrelevant", "leaning": "", "children": []}},
{"claim": "New Zealand Labour Party is talking about a forced coronavirus vaccination", "id": 29, "source": "AFP Fact Check New Zealand", "root_tweet": {"id": 1296572655261192192, "text": "", "stance": "Discussing", "leaning": "", "children": []}},
{"claim": "New Zealand Labour Party is talking about a forced coronavirus vaccination", "id": 29, "source": "AFP Fact Check New Zealand", "root_tweet": {"id": 1295728378176131072, "text": "", "stance": "Supporting", "leaning": "", "children": []}},
{"claim": "New Zealand Labour Party is talking about a forced coronavirus vaccination", "id": 29, "source": "AFP Fact Check New Zealand", "root_tweet": {"id": 1285924752419414017, "text": "", "stance": "Discussing", "leaning": "Refuting", "children": []}},
{"claim": "New Zealand Labour Party is talking about a forced coronavirus vaccination", "id": 29, "source": "AFP Fact Check New Zealand", "root_tweet": {"id": 1296117208175669248, "text": "", "stance": "Irrelevant", "leaning": "", "children": []}},
{"claim": "New Zealand Labour Party is talking about a forced coronavirus vaccination", "id": 29, "source": "AFP Fact Check New Zealand", "root_tweet": {"id": 1296798183746674689, "text": "", "stance": "Irrelevant", "leaning": "", "children": []}},
{"claim": "New Zealand Labour Party is talking about a forced coronavirus vaccination", "id": 29, "source": "AFP Fact Check New Zealand", "root_tweet": {"id": 1299341081784528896, "text": "", "stance": "Irrelevant", "leaning": "", "children": []}},
{"claim": "New Zealand Labour Party is talking about a forced coronavirus vaccination", "id": 29, "source": "AFP Fact Check New Zealand", "root_tweet": {"id": 1308768828369907712, "text": "", "stance": "Irrelevant", "leaning": "", "children": []}},
{"claim": "New Zealand Labour Party is talking about a forced coronavirus vaccination", "id": 29, "source": "AFP Fact Check New Zealand", "root_tweet": {"id": 1296513042147139585, "text": "", "stance": "Discussing", "leaning": "", "children": []}},
{"claim": "New Zealand Labour Party is talking about a forced coronavirus vaccination", "id": 29, "source": "AFP Fact Check New Zealand", "root_tweet": {"id": 1296556295642681346, "text": "", "stance": "Discussing", "leaning": "", "children": []}},
{"claim": "New Zealand Labour Party is talking about a forced coronavirus vaccination", "id": 29, "source": "AFP Fact Check New Zealand", "root_tweet": {"id": 1294539039177977856, "text": "", "stance": "Supporting", "leaning": "", "children": [{"id": 1294579402764775425, "text": "", "stance": "Discussing", "leaning": "Supporting", "children": [{"id": 1294582620240543746, "text": "", "stance": "Discussing", "leaning": "Supporting", "children": []}]}]}},
{"claim": "New Zealand Labour Party is talking about a forced coronavirus vaccination", "id": 29, "source": "AFP Fact Check New Zealand", "root_tweet": {"id": 1295891154081325056, "text": "", "stance": "Irrelevant", "leaning": "", "children": []}},
{"claim": "New Zealand Labour Party is talking about a forced coronavirus vaccination", "id": 29, "source": "AFP Fact Check New Zealand", "root_tweet": {"id": 1296691337568366593, "text": "", "stance": "Irrelevant", "leaning": "", "children": []}},
{"claim": "New Zealand Labour Party is talking about a forced coronavirus vaccination", "id": 29, "source": "AFP Fact Check New Zealand", "root_tweet": {"id": 1299346461369528321, "text": "", "stance": "Irrelevant", "leaning": "", "children": []}},
{"claim": "New Zealand Labour Party is talking about a forced coronavirus vaccination", "id": 29, "source": "AFP Fact Check New Zealand", "root_tweet": {"id": 1296040336574169088, "text": "", "stance": "Irrelevant", "leaning": "", "children": []}},
{"claim": "New Zealand Labour Party is talking about a forced coronavirus vaccination", "id": 29, "source": "AFP Fact Check New Zealand", "root_tweet": {"id": 1296053845076971520, "text": "", "stance": "Discussing", "leaning": "", "children": []}},
{"claim": "New Zealand Labour Party is talking about a forced coronavirus vaccination", "id": 29, "source": "AFP Fact Check New Zealand", "root_tweet": {"id": 1299365253436801024, "text": "", "stance": "Irrelevant", "leaning": "", "children": []}},
{"claim": "New Zealand Labour Party is talking about a forced coronavirus vaccination", "id": 29, "source": "AFP Fact Check New Zealand", "root_tweet": {"id": 1295798224717062147, "text": "", "stance": "Irrelevant", "leaning": "", "children": []}},
{"claim": "New Zealand Labour Party is talking about a forced coronavirus vaccination", "id": 29, "source": "AFP Fact Check New Zealand", "root_tweet": {"id": 1300026752844980226, "text": "", "stance": "Discussing", "leaning": "", "children": []}},
{"claim": "New Zealand Labour Party is talking about a forced coronavirus vaccination", "id": 29, "source": "AFP Fact Check New Zealand", "root_tweet": {"id": 1296137684797202432, "text": "", "stance": "Irrelevant", "leaning": "", "children": []}},
{"claim": "New Zealand Labour Party is talking about a forced coronavirus vaccination", "id": 29, "source": "AFP Fact Check New Zealand", "root_tweet": {"id": 1297449096874254336, "text": "", "stance": "Irrelevant", "leaning": "", "children": []}},
{"claim": "New Zealand Labour Party is talking about a forced coronavirus vaccination", "id": 29, "source": "AFP Fact Check New Zealand", "root_tweet": {"id": 1295929242425982976, "text": "", "stance": "Irrelevant", "leaning": "", "children": []}},
{"claim": "New Zealand Labour Party is talking about a forced coronavirus vaccination", "id": 29, "source": "AFP Fact Check New Zealand", "root_tweet": {"id": 1315921826510446592, "text": "", "stance": "Discussing", "leaning": "Refuting", "children": []}},
{"claim": "New Zealand Labour Party is talking about a forced coronavirus vaccination", "id": 29, "source": "AFP Fact Check New Zealand", "root_tweet": {"id": 1298373764669997058, "text": "", "stance": "Irrelevant", "leaning": "", "children": []}},
{"claim": "New Zealand Labour Party is talking about a forced coronavirus vaccination", "id": 29, "source": "AFP Fact Check New Zealand", "root_tweet": {"id": 1336255870620086272, "text": "", "stance": "Discussing", "leaning": "Refuting", "children": []}},
{"claim": "New Zealand Labour Party is talking about a forced coronavirus vaccination", "id": 29, "source": "AFP Fact Check New Zealand", "root_tweet": {"id": 1297657141130559488, "text": "", "stance": "Discussing", "leaning": "", "children": []}},
{"claim": "New Zealand Labour Party is talking about a forced coronavirus vaccination", "id": 29, "source": "AFP Fact Check New Zealand", "root_tweet": {"id": 1296116515335364609, "text": "", "stance": "Irrelevant", "leaning": "", "children": [{"id": 1296161437908267010, "text": "", "stance": "Supporting", "leaning": "", "children": []}]}},
{"claim": "New Zealand Labour Party is talking about a forced coronavirus vaccination", "id": 29, "source": "AFP Fact Check New Zealand", "root_tweet": {"id": 1327993521886928896, "text": "", "stance": "Irrelevant", "leaning": "", "children": [{"id": 1328008308427423744, "text": "", "stance": "Discussing", "leaning": "Supporting", "children": []}]}},
{"claim": "New Zealand Labour Party is talking about a forced coronavirus vaccination", "id": 29, "source": "AFP Fact Check New Zealand", "root_tweet": {"id": 1293792740623265793, "text": "", "stance": "Irrelevant", "leaning": "", "children": [{"id": 1293805338336980992, "text": "", "stance": "Discussing", "leaning": "Supporting", "children": []}]}},
{"claim": "New Zealand Labour Party is talking about a forced coronavirus vaccination", "id": 29, "source": "AFP Fact Check New Zealand", "root_tweet": {"id": 1327977247823732736, "text": "", "stance": "Irrelevant", "leaning": "", "children": [{"id": 1328026849784573953, "text": "", "stance": "Supporting", "leaning": "", "children": [{"id": 1328070255273410560, "text": "", "stance": "Irrelevant", "leaning": "", "children": []}]}]}},
{"claim": "New Zealand Labour Party is talking about a forced coronavirus vaccination", "id": 29, "source": "AFP Fact Check New Zealand", "root_tweet": {"id": 1273971458923008000, "text": "", "stance": "Irrelevant", "leaning": "", "children": [{"id": 1274003232294162432, "text": "", "stance": "Discussing", "leaning": "Refuting", "children": []}]}},
{"claim": "New Zealand Labour Party is talking about a forced coronavirus vaccination", "id": 29, "source": "AFP Fact Check New Zealand", "root_tweet": {"id": 1324446353930506242, "text": "", "stance": "Discussing", "leaning": "", "children": [{"id": 1324447290623324161, "text": "", "stance": "Refuting", "leaning": "", "children": [{"id": 1324447519883948032, "text": "", "stance": "Discussing", "leaning": "Refuting", "children": [{"id": 1324449309186732033, "text": "", "stance": "Irrelevant", "leaning": "", "children": []}]}, {"id": 1324448484179775489, "text": "", "stance": "Irrelevant", "leaning": "", "children": [{"id": 1324448903199154176, "text": "", "stance": "Irrelevant", "leaning": "", "children": [{"id": 1324450310992007168, "text": "", "stance": "Irrelevant", "leaning": "", "children": [{"id": 1324450587807674368, "text": "", "stance": "Irrelevant", "leaning": "", "children": []}]}]}]}]}]}},
{"claim": "New Zealand Labour Party is talking about a forced coronavirus vaccination", "id": 29, "source": "AFP Fact Check New Zealand", "root_tweet": {"id": 1295959030280548353, "text": "", "stance": "Irrelevant", "leaning": "", "children": [{"id": 1295961693424517121, "text": "", "stance": "Discussing", "leaning": "Refuting", "children": []}]}},
{"claim": "New Zealand Labour Party is talking about a forced coronavirus vaccination", "id": 29, "source": "AFP Fact Check New Zealand", "root_tweet": {"id": 1315912456208752640, "text": "", "stance": "Discussing", "leaning": "", "children": [{"id": 1315931916051382272, "text": "", "stance": "Irrelevant", "leaning": "", "children": [{"id": 1315990773268127757, "text": "", "stance": "Supporting", "leaning": "", "children": [{"id": 1316142128997818370, "text": "", "stance": "Discussing", "leaning": "Refuting", "children": [{"id": 1316266638963101696, "text": "", "stance": "Discussing", "leaning": "Supporting", "children": []}]}, {"id": 1316299460519944193, "text": "", "stance": "Discussing", "leaning": "Refuting", "children": [{"id": 1316421480801075202, "text": "", "stance": "Discussing", "leaning": "Supporting", "children": [{"id": 1317732496633516032, "text": "", "stance": "Discussing", "leaning": "Refuting", "children": []}]}]}]}]}]}},
{"claim": "New Zealand Labour Party is talking about a forced coronavirus vaccination", "id": 29, "source": "AFP Fact Check New Zealand", "root_tweet": {"id": 1260835505966465026, "text": "", "stance": "Irrelevant", "leaning": "", "children": [{"id": 1261091102427209729, "text": "", "stance": "Irrelevant", "leaning": "", "children": [{"id": 1261098741102080000, "text": "", "stance": "Irrelevant", "leaning": "", "children": [{"id": 1261132352064909314, "text": "", "stance": "Irrelevant", "leaning": "", "children": [{"id": 1261139491051278337, "text": "", "stance": "Supporting", "leaning": "", "children": [{"id": 1261141262859595782, "text": "", "stance": "Discussing", "leaning": "Supporting", "children": [{"id": 1261142776034373634, "text": "", "stance": "Discussing", "leaning": "Refuting", "children": [{"id": 1261143427992834049, "text": "", "stance": "Refuting", "leaning": "", "children": [{"id": 1261145546980384777, "text": "", "stance": "Irrelevant", "leaning": "", "children": [{"id": 1261184150402408448, "text": "", "stance": "Irrelevant", "leaning": "", "children": [{"id": 1261222160246247425, "text": "", "stance": "Irrelevant", "leaning": "", "children": []}]}]}]}]}]}]}]}]}]}]}},
{"claim": "New Zealand Labour Party is talking about a forced coronavirus vaccination", "id": 29, "source": "AFP Fact Check New Zealand", "root_tweet": {"id": 1344206765076983809, "text": "", "stance": "Irrelevant", "leaning": "", "children": [{"id": 1344229394156564480, "text": "", "stance": "Irrelevant", "leaning": "", "children": [{"id": 1344234587615064065, "text": "", "stance": "Irrelevant", "leaning": "", "children": [{"id": 1344244597581606913, "text": "", "stance": "Irrelevant", "leaning": "", "children": [{"id": 1344246341795459074, "text": "", "stance": "Irrelevant", "leaning": "", "children": [{"id": 1344264644999991297, "text": "", "stance": "Irrelevant", "leaning": "", "children": [{"id": 1344279825381527553, "text": "", "stance": "Irrelevant", "leaning": "", "children": [{"id": 1344307515979395072, "text": "", "stance": "Irrelevant", "leaning": "", "children": [{"id": 1344308288628936704, "text": "", "stance": "Irrelevant", "leaning": "", "children": [{"id": 1344318404119961608, "text": "", "stance": "Irrelevant", "leaning": "", "children": [{"id": 1344319587584778241, "text": "", "stance": "Irrelevant", "leaning": "", "children": [{"id": 1344322089176727558, "text": "", "stance": "Irrelevant", "leaning": "", "children": [{"id": 1344322710739034113, "text": "", "stance": "Irrelevant", "leaning": "", "children": [{"id": 1344324866699358218, "text": "", "stance": "Irrelevant", "leaning": "", "children": [{"id": 1344327277744676864, "text": "", "stance": "Irrelevant", "leaning": "", "children": [{"id": 1344332629856935936, "text": "", "stance": "Refuting", "leaning": "", "children": []}]}]}]}]}]}]}]}]}]}]}]}]}]}]}]}}]